surebilling
