Metadata-Version: 1.1
Name: surebilling
Version: 1.2
Summary: Python wrapper for the SureBilling API
Home-page: http://surebilling.com
Author: SureBilling Inc.
Author-email: admin@surebilling.com
License: UNKNOWN
Platform: UNKNOWN
Classifier: Intended Audience :: Developers
Classifier: Programming Language :: Python
Classifier: Environment :: Console
Classifier: Environment :: MacOS X
Classifier: Intended Audience :: Financial and Insurance Industry
Classifier: License :: Other/Proprietary License
Classifier: Topic :: Office/Business :: Financial :: Accounting
